are/__init__.py
are/simulation/CONCEPTS.md
are/simulation/__init__.py
are/simulation/benchmark.py
are/simulation/config.py
are/simulation/dataset_helpers.py
are/simulation/environment.py
are/simulation/exceptions.py
are/simulation/logging_config.py
are/simulation/main.py
are/simulation/multi_scenario_runner.py
are/simulation/notification_system.py
are/simulation/priority_queue.py
are/simulation/replay.py
are/simulation/scenario_runner.py
are/simulation/time_manager.py
are/simulation/tool_box.py
are/simulation/tool_utils.py
are/simulation/tools.py
are/simulation/types.py
are/simulation/agents/README.md
are/simulation/agents/adapters.py
are/simulation/agents/agent_builder.py
are/simulation/agents/agent_config_builder.py
are/simulation/agents/agent_execution_result.py
are/simulation/agents/agent_log.py
are/simulation/agents/are_simulation_agent.py
are/simulation/agents/are_simulation_agent_config.py
are/simulation/agents/decoding_types.py
are/simulation/agents/multimodal.py
are/simulation/agents/user_proxy.py
are/simulation/agents/default_agent/agent_factory.py
are/simulation/agents/default_agent/app_agent.py
are/simulation/agents/default_agent/are_simulation_main.py
are/simulation/agents/default_agent/base_agent.py
are/simulation/agents/default_agent/default_tools.py
are/simulation/agents/default_agent/prompts/__init__.py
are/simulation/agents/default_agent/prompts/additional_prompts.py
are/simulation/agents/default_agent/prompts/notification_system.py
are/simulation/agents/default_agent/prompts/system_prompt.py
are/simulation/agents/default_agent/steps/are_simulation.py
are/simulation/agents/default_agent/termination_methods/are_simulation.py
are/simulation/agents/default_agent/tools/action_executor.py
are/simulation/agents/default_agent/tools/json_action_executor.py
are/simulation/agents/default_agent/utils/logging_utils.py
are/simulation/agents/llm/exceptions.py
are/simulation/agents/llm/llm_engine.py
are/simulation/agents/llm/llm_engine_builder.py
meta_agents_research_environments-1.2.0.dist-info/METADATA
meta_agents_research_environments-1.2.0.dist-info/WHEEL
meta_agents_research_environments-1.2.0.dist-info/entry_points.txt
meta_agents_research_environments-1.2.0.dist-info/licenses/LICENSE
meta_agents_research_environments-1.2.0.dist-info/RECORD
