Metadata-Version: 2.4
Name: meta-agents-research-environments
Version: 1.2.0
Summary: Meta Agents Research Environments is a research-driven environment designed to simulate complex, real-life tasks that span several minutes and require multiple steps to be solved. Unlike static simulation environments, this platform introduces a dynamic setting where the state of the environment evolves and new information is continuously integrated.
Project-URL: Homepage, https://github.com/facebookresearch/meta-agents-research-environments/
Project-URL: Repository, https://github.com/facebookresearch/meta-agents-research-environments.git
License: MIT License
License-File: LICENSE
Requires-Python: >=3.10
Requires-Dist: click==8.1.8
Requires-Dist: datasets==4.0.0
Requires-Dist: docstring-parser==0.16
Requires-Dist: fsspec==2024.12.0
Requires-Dist: huggingface-hub==0.33.4
Requires-Dist: inputimeout==1.0.4
Requires-Dist: jinja2==3.1.6
Requires-Dist: litellm==1.71.1
Requires-Dist: mammoth==1.8.0
Requires-Dist: markdownify==0.14.1
Requires-Dist: mcp[cli]==1.11.0
Requires-Dist: numpy==2.2.6
Requires-Dist: pandas==2.2.3
Requires-Dist: pdfminer-six==20231228
Requires-Dist: pillow==11.1.0
Requires-Dist: polars-lts-cpu==1.33.1
Requires-Dist: puremagic==1.27
Requires-Dist: pydantic==2.10.6
Requires-Dist: python-dotenv==1.0.1
Requires-Dist: python-pptx==1.0.2
Requires-Dist: rapidfuzz==3.12.1
Requires-Dist: termcolor==2.5.0
Provides-Extra: dev
Requires-Dist: autoflake==2.3.1; extra == 'dev'
Requires-Dist: build==1.2.1; extra == 'dev'
Requires-Dist: codespell==2.4.1; extra == 'dev'
Requires-Dist: debugpy==1.8.12; extra == 'dev'
Requires-Dist: flake8-tidy-imports==4.11.0; extra == 'dev'
Requires-Dist: flake8==7.1.1; extra == 'dev'
Requires-Dist: hatchling==1.21.1; extra == 'dev'
Requires-Dist: pre-commit==2.21.0; extra == 'dev'
Requires-Dist: pyright==1.1.406; extra == 'dev'
Requires-Dist: pytest==8.3.4; extra == 'dev'
Requires-Dist: ruff==0.11.5; extra == 'dev'
Requires-Dist: twine==5.0.0; extra == 'dev'
Requires-Dist: typer==0.16.0; extra == 'dev'
Provides-Extra: gui
Requires-Dist: fastapi==0.116.1; extra == 'gui'
Requires-Dist: pypdf==6.0.0; extra == 'gui'
Requires-Dist: starlette==0.47.2; extra == 'gui'
Requires-Dist: strawberry-graphql==0.275.5; extra == 'gui'
Requires-Dist: uvicorn==0.35.0; extra == 'gui'
Requires-Dist: wsproto==1.2.0; extra == 'gui'
